{"cameraMode":{"drawMode":0,"name":"Shaded","section":"Shading Mode"},"sceneLighting":true,"audioPlay":false,"sceneViewState":{"m_AlwaysRefresh":false,"showFog":true,"showSkybox":true,"showFlares":true,"showImageEffects":true,"showParticleSystems":true,"showVisualEffectGraphs":true,"m_FxEnabled":true},"in2DMode":false,"pivot":{"x":262.3958435058594,"y":70.57984924316406,"z":-125.03719329833985},"rotation":{"x":0.11958374828100205,"y":0.6564244627952576,"z":-0.1064777746796608,"w":0.737210750579834},"size":15.05257797241211,"orthographic":false}